py_api_lib/__init__.py
py_api_lib/_build_config.py
py_api_lib/_runtime_config.py
py_api_lib/api_client.py
py_api_lib/api_lib.py
py_api_lib/api_logger.py
py_api_lib/exceptions.py
py_api_lib/extensions.py
py_api_lib/usage_examples.py
py_api_lib_system/__init__.py
py_api_lib_system/_build_config.py
py_api_lib_system/_runtime_config.py
py_api_lib_system/api_client.py
py_api_lib_system/api_lib.py
py_api_lib_system/api_logger.py
py_api_lib_system/exceptions.py
py_api_lib_system/extensions.py
py_api_lib_system/usage_examples.py
pymodel_system/__init__.py
pymodel_system/schema_metadata.py
pymodel_system/serialization_errors.py
pymodel_system/enums/__init__.py
pymodel_system/enums/billing_plan_types.py
pymodel_system/enums/invocation_status.py
pymodel_system/enums/plugin_auth_type.py
pymodel_system/enums/plugin_health_status.py
pymodel_system/enums/time_zones.py
pymodel_system/objects/__init__.py
pymodel_system/objects/api_key.py
pymodel_system/objects/audit_log.py
pymodel_system/objects/build.py
pymodel_system/objects/build_artifact.py
pymodel_system/objects/build_download.py
pymodel_system/objects/client_sdk.py
pymodel_system/objects/country_data.py
pymodel_system/objects/domain.py
pymodel_system/objects/feature_flag.py
pymodel_system/objects/gatekeeper.py
pymodel_system/objects/global_system_config.py
pymodel_system/objects/license_activation.py
pymodel_system/objects/license_key.py
pymodel_system/objects/license_payment.py
pymodel_system/objects/license_promo.py
pymodel_system/objects/license_usage.py
pymodel_system/objects/platform_billing_contract.py
pymodel_system/objects/platform_billing_invoice.py
pymodel_system/objects/platform_billing_payment_method.py
pymodel_system/objects/platform_billing_plan.py
pymodel_system/objects/platform_billing_subscription.py
pymodel_system/objects/platform_billing_usage.py
pymodel_system/objects/plugin_invocation_log.py
pymodel_system/objects/plugin_registry.py
pymodel_system/objects/project.py
supero-1.0.2.dist-info/METADATA
supero-1.0.2.dist-info/WHEEL
supero-1.0.2.dist-info/entry_points.txt
supero-1.0.2.dist-info/top_level.txt
supero-1.0.2.dist-info/RECORD
