Metadata-Version: 2.4
Name: supero
Version: 1.0.2
Summary: Unified SDK for Supero platform - includes intuitive wrapper (supero) and low-level API client (py_api_lib)
Author-email: Supero Team <support@supero.io>
License: MIT
Project-URL: Homepage, https://github.com/yourusername/supero
Project-URL: Documentation, https://supero.readthedocs.io
Project-URL: Repository, https://github.com/yourusername/supero
Project-URL: Bug Tracker, https://github.com/yourusername/supero/issues
Project-URL: Changelog, https://github.com/yourusername/supero/blob/main/CHANGELOG.md
Keywords: api,sdk,orm,crud,supero,api-client
Classifier: Development Status :: 4 - Beta
Classifier: Intended Audience :: Developers
Classifier: Programming Language :: Python :: 3
Classifier: Programming Language :: Python :: 3.8
Classifier: Programming Language :: Python :: 3.9
Classifier: Programming Language :: Python :: 3.10
Classifier: Programming Language :: Python :: 3.11
Classifier: License :: OSI Approved :: MIT License
Classifier: Operating System :: OS Independent
Requires-Python: >=3.8
Requires-Dist: requests>=2.28.0
Requires-Dist: inflection>=0.5.1
Requires-Dist: gevent>=22.10.0
Requires-Dist: cryptography>=41.0.0
Provides-Extra: dev
Requires-Dist: pytest>=7.4.0; extra == "dev"
Requires-Dist: pytest-cov>=4.1.0; extra == "dev"
Requires-Dist: pytest-mock>=3.11.0; extra == "dev"
Requires-Dist: coverage>=7.3.0; extra == "dev"
Requires-Dist: black>=23.7.0; extra == "dev"
Requires-Dist: flake8>=6.1.0; extra == "dev"
Requires-Dist: mypy>=1.5.0; extra == "dev"
Provides-Extra: test
Requires-Dist: pytest>=7.4.0; extra == "test"
Requires-Dist: pytest-cov>=4.1.0; extra == "test"
Requires-Dist: pytest-mock>=3.11.0; extra == "test"
Requires-Dist: coverage>=7.3.0; extra == "test"
Provides-Extra: docs
Requires-Dist: sphinx>=7.2.0; extra == "docs"
Requires-Dist: sphinx-rtd-theme>=1.3.0; extra == "docs"
Provides-Extra: all
Requires-Dist: supero[dev,docs,test]; extra == "all"
